{
    "chunk_id": "f3553c46-484e-43cb-8207-5f83bd8b707a",
    "type": "image",
    "content": "The image presents a flowchart illustrating the organizational structure of a company, with a focus on the roles and responsibilities within the organization. The chart is divided into several sections, each representing a different department or function.\n\n* **Gérant (Manager)**\n\t+ Located at the top center of the chart\n\t+ No statistics presented\n* **Responsable Maintenance (Maintenance Manager)**\n\t+ Located to the left of the Gérant\n\t+ No statistics presented\n\t+ Subordinates:\n\t\t- Groupe 1\n\t\t- Groupe 2\n\t\t- CAO\n\t\t- Controle Qualité\n* **Responsable Production et Alimentation Sous Traitant (Production and Subcontracting Manager)**\n\t+ Located below the Gérant\n\t+ No statistics presented\n\t+ Subordinates:\n\t\t- Magasin Import-Export\n\t\t- Coupe\n* **Secrétaire de Direction (Secretary of Direction)**\n\t+ Located to the right of the Gérant\n\t+ No statistics presented\n\t+ Subordinate:\n\t\t- Secrétaire Administrative\n* **Responsable Qualité et Sous Traitance (Quality and Subcontracting Manager)**\n\t+ Located to the right of the Secrétaire de Direction\n\t+ No statistics presented\n\t+ Subordinate:\n\t\t- Controle Qualité Sous-Traitant\n\nIn summary, the image provides a clear visual representation of the company's organizational structure, highlighting the key roles and responsibilities within each department. The chart effectively illustrates the hierarchical relationships between the different positions, making it easy to understand the flow of authority and communication within the organization.",
    "metadata": {
        "source": "C:\\Users\\hp\\AppData\\Local\\Temp\\tmp82mbmkdi.png",
        "image_index": 1
    }
}